nt_flash.py
nt_flash-1.0.2.dist-info/METADATA
nt_flash-1.0.2.dist-info/WHEEL
nt_flash-1.0.2.dist-info/entry_points.txt
nt_flash-1.0.2.dist-info/top_level.txt
nt_flash-1.0.2.dist-info/RECORD
