Metadata-Version: 2.4
Name: nt-flash
Version: 1.0.2
Summary: Flash firmware to Expert Sleepers Disting NT Eurorack module
Author-email: Neal Sanche <neal@nosuch.com>
License-Expression: MIT
Project-URL: Homepage, https://github.com/thorinside/nt_helper
Project-URL: Repository, https://github.com/thorinside/nt_helper
Project-URL: Issues, https://github.com/thorinside/nt_helper/issues
Keywords: disting,eurorack,firmware,flash,expert-sleepers
Classifier: Development Status :: 4 - Beta
Classifier: Environment :: Console
Classifier: Intended Audience :: End Users/Desktop
Classifier: Operating System :: MacOS
Classifier: Operating System :: Microsoft :: Windows
Classifier: Operating System :: POSIX :: Linux
Classifier: Programming Language :: Python :: 3
Classifier: Programming Language :: Python :: 3.9
Classifier: Programming Language :: Python :: 3.10
Classifier: Programming Language :: Python :: 3.11
Classifier: Programming Language :: Python :: 3.12
Classifier: Programming Language :: Python :: 3.13
Classifier: Topic :: Multimedia :: Sound/Audio
Classifier: Topic :: System :: Hardware
Requires-Python: >=3.9
Requires-Dist: spsdk>=3.0.0
